[
	{
		"model": "movies.mbti",
		"pk": 13,
		"fields": {
			"release_date": "2016-02-09",
			"title": "데드풀",
			"poster_path": "/lljWMCR3CZcMv75gII3Q2FsLLN3.jpg",
			"vote_average": 7.6,
			"overview": "특수부대 요원 출신의 용병 웨이드 윌슨은 취향과 장난기마저 똑 닮은 바네사를 만나 행복한 나날을 보낸다. 하지만 행복은 광고처럼 짧은 법. 말기 암 선고를 받은 웨이드는 비밀 임상실험에 참여하며 재기를 노린다. 극한의 고문으로 이뤄진 실험 후 웨이드는 암을 치료할뿐더러 무한한 재생 능력을 얻으며 불사의 존재가 된다. 하지만 동시에 부작용으로 호러영화에 어울릴 법한 외양을 갖는다. 스스로 슈트까지 지어 입고 데드풀이 된 웨이드는 자신을 고문한 자를 찾아 제대로 복수한 뒤 당당히 바네사 앞에 나서려 한다.",
			"genre": "액션",
			"mbti": "istp"
		}
	},
	{
		"model": "movies.mbti",
		"pk": 14,
		"fields": {
			"release_date": "2012-03-12",
			"title": "헝거게임: 판엠의 불꽃",
			"poster_path": "/iZWZcLJ2NoyM1UoDJexgSWmXOC.jpg",
			"vote_average": 7.2,
			"overview": "12개의 구역으로 이루어진 독재국가 ‘판엠’이 체제를 유지하기 위해 만든 생존 전쟁 ‘헝거게임’. 일년에 한번 각 구역에서 추첨을 통해 두 명을 선발, 총 24명이 생존을 겨루게 되는 것. ‘헝거게임’의 추첨식에서 ‘캣니스’는 어린 여동생의 이름이 호명되자 동생을 대신해 참가를 자청하며 주목을 받는다. 과거 자신을 위기에서 구해줬던 ‘피타’ 역시 선발되어 미묘한 감정에 휩싸인다. ‘캣니스’는 금지구역에서 함께 사냥했던 ‘게일’에게 가족을 부탁하며 생존을 겨루게 될 판엠의 수도 ‘캐피톨’로 향하는데...",
			"genre": "SF",
			"mbti": "istp"
		}
	},
	{
		"model": "movies.mbti",
		"pk": 15,
		"fields": {
			"release_date": "2010-07-15",
			"title": "인셉션",
			"poster_path": "/jSm8mzp7sucgL8NwINIoAmx4dS5.jpg",
			"vote_average": 8.3,
			"overview": "타인의 꿈과 접속해 생각을 빼낼 수 있는 근미래, 돔 코브는 꿈의 보안 프로그래머이자 동시에 침입자다. 그는 일본인 사업가 사이토의 제안에 따라 거대 합병 기업의 총수가 될 피셔의 꿈을 설계하여 기업 합병을 막으려 든다. 그 일을 성사시키면 코브는 사이토의 도움으로 아내의 살해범으로 몰린 자신의 누명을 뒤로 하고 사랑스런 자녀들이 있는 집으로 돌아갈 수 있다. 마침내 코브 일행은 꿈 안의 꿈 안의 또 꿈이라는 경로를 거치며 피셔의 꿈과 무의식 깊숙한 곳을 설계하고 침투한다.",
			"genre": "액션",
			"mbti": "istp"
		}
	},
	{
		"model": "movies.mbti",
		"pk": 16,
		"fields": {
			"release_date": "2014-11-05",
			"title": "인터스텔라",
			"poster_path": "/zDNAeWU0PxKolEX1D8Vn1qWhGjH.jpg",
			"vote_average": 8.3,
			"overview": "세계 각국의 정부와 경제가 완전히 붕괴된 미래가 다가온다. 지난 20세기에 범한 잘못이 전 세계적인 식량 부족을 불러왔고, NASA도 해체되었다. 나사 소속 우주비행사였던 쿠퍼는 지구에 몰아친 식량난으로 옥수수나 키우며 살고 있다. 거센 황사가 몰아친 어느 날 알 수 없는 힘에 이끌려 딸과 함께 도착한 곳은 인류가 이주할 행성을 찾는 나사의 비밀본부. 이 때 시공간에 불가사의한 틈이 열리고, 이 곳을 탐험해 인류를 구해야 하는 임무를 위해 쿠퍼는 만류하는 딸을 뒤로한 채 우주선에 탑승하는데...",
			"genre": "모험",
			"mbti": "istp"
		}
	}
]